pip3_autoremove.py
only_pip3_autoremove-0.1.1.dist-info/entry_points.txt
only_pip3_autoremove-0.1.1.dist-info/LICENSE
only_pip3_autoremove-0.1.1.dist-info/WHEEL
only_pip3_autoremove-0.1.1.dist-info/METADATA
only_pip3_autoremove-0.1.1.dist-info/RECORD
