Metadata-Version: 2.1
Name: only-pip3-autoremove
Version: 0.1.1
Summary: Remove a package and its unused dependencies
Author: JohnDevlopment, invlpg
Requires-Python: >=3.8
Classifier: Intended Audience :: Developers
Classifier: License :: OSI Approved :: Apache Software License
Classifier: Programming Language :: Python
Classifier: Programming Language :: Python :: 3
Requires-Dist: pip
Requires-Dist: setuptools
Project-URL: Homepage, https://github.com/JohnDevlopment/pip3-autoremove
Project-URL: OriginalSource, https://github.com/invl/pip-autoremove
Project-URL: Source, https://github.com/JohnDevlopment/pip3-autoremove
